pyassist_webutils/__init__.py
pyassist_webutils/scraper/__init__.py
pyassist_webutils/scraper/bs4.py
pyassist_webutils/scraper/pandas.py
pyassist_webutils/scraper/request.py
pyassist_webutils/scraper/selenium.py
pyassist_webutils-0.1.1a2.dist-info/LICENSE
pyassist_webutils-0.1.1a2.dist-info/METADATA
pyassist_webutils-0.1.1a2.dist-info/WHEEL
pyassist_webutils-0.1.1a2.dist-info/RECORD
