Metadata-Version: 2.3
Name: pyassist-webutils
Version: 0.1.1a2
Summary: 
Author: ISabariRajan
Requires-Python: >=3.12,<4.0
Classifier: Programming Language :: Python :: 3
Classifier: Programming Language :: Python :: 3.12
Classifier: Programming Language :: Python :: 3.13
Requires-Dist: beautifulsoup4 (>=4.12.3,<5.0.0)
Requires-Dist: lxml (>=5.3.0,<6.0.0)
Requires-Dist: openpyxl (>=3.1.5,<4.0.0)
Requires-Dist: pandas (>=2.2.3,<3.0.0)
Requires-Dist: pyassist-utils (>=0.0.1,<0.0.2)
Requires-Dist: requests (>=2.32.3,<3.0.0)
